{"name": "Nue", "pic_url": "https://vignette4.wikia.nocookie.net/mira-miracle/images/1/1c/Nue.png/revision/latest?cb=20160910150241&amp;format=original", "atk": "6500/7757", "hp": "9800/11694", "bond": [{"name": "Raiju > Nue", "value": "Increases Nue's Skill DMG by 4%"}], "skill": [{"name": "Summon Fanged Beast", "value": "Deals 3922/4682 DMG to current target, with a moderate chance of inflicting Stun."}], "ability": [{"name": "Beast Factor (Lv. 39)", "value": "Moderately increases crit rate."}, {"name": "Magical Beast Factor (Lv. 78)", "value": "Significantly increases crit damage."}]}